salt_napalm-2019.1.0a2-py2.7-nspkg.pth
salt_napalm/__version__.py
salt_napalm/cli.py
salt_napalm/parsers.py
salt_napalm/scripts.py
salt_napalm/_roster/ansible.py
salt_napalm/_roster/locations.py
salt_napalm/_runners/napalm.py
salt_napalm/_runners/napalm.pyc
salt_napalm-2019.1.0a2.dist-info/DESCRIPTION.rst
salt_napalm-2019.1.0a2.dist-info/METADATA
salt_napalm-2019.1.0a2.dist-info/RECORD
salt_napalm-2019.1.0a2.dist-info/WHEEL
salt_napalm-2019.1.0a2.dist-info/entry_points.txt
salt_napalm-2019.1.0a2.dist-info/metadata.json
salt_napalm-2019.1.0a2.dist-info/namespace_packages.txt
salt_napalm-2019.1.0a2.dist-info/top_level.txt
