Metadata-Version: 2.0
Name: salt-napalm
Version: 2019.1.0a2
Summary: Salt plugin for interacting with network devices through NAPALM, without running Minions
Home-page: https://github.com/napalm-automation/napalm-salt
Author: Mircea Ulinic
Author-email: mircea.ulinic@gmail.com
License: Apache License 2.0
Keywords: napalm,salt,network,automation,cli
Platform: UNKNOWN
Classifier: Development Status :: 3 - Alpha
Classifier: Topic :: Utilities
Classifier: Topic :: System :: Networking
Classifier: Programming Language :: Python
Classifier: Programming Language :: Python :: 2
Classifier: Programming Language :: Python :: 2.7
Classifier: Programming Language :: Python :: 3
Classifier: Programming Language :: Python :: 3.4
Classifier: Programming Language :: Python :: 3.5
Classifier: Programming Language :: Python :: 3.6
Classifier: Operating System :: POSIX :: Linux
Classifier: Operating System :: POSIX :: Linux
Classifier: Operating System :: MacOS
Classifier: Intended Audience :: Developers
Requires-Dist: salt
Requires-Dist: napalm
